swiftspec/__init__.py
swiftspec/_version.py
swiftspec/core.py
swiftspec-0.0.4.dist-info/LICENSE
swiftspec-0.0.4.dist-info/METADATA
swiftspec-0.0.4.dist-info/WHEEL
swiftspec-0.0.4.dist-info/entry_points.txt
swiftspec-0.0.4.dist-info/top_level.txt
swiftspec-0.0.4.dist-info/RECORD
