Metadata-Version: 2.1
Name: swiftspec
Version: 0.0.4
Summary: fsspec implementation for OpenStack SWIFT
Home-page: https://github.com/fsspec/swiftspec
Author: Tobias Kölling
Author-email: tobias.koelling@mpimet.mpg.de
License: UNKNOWN
Platform: UNKNOWN
Classifier: Programming Language :: Python :: 3
Classifier: License :: OSI Approved :: MIT License
Classifier: Operating System :: OS Independent
Requires-Python: >=3.7
License-File: LICENSE
Requires-Dist: fsspec (>=0.9.0)
Requires-Dist: aiohttp
